{
	"experience": {
		"Mid-Senior level": 43.93,
		"Entry level": 38.87,
		"Associate": 10.4,
		"Director": 3.97,
		"Internship": 1.53,
		"Executive": 1.29
	},
	"typeWork": {
		"Full-time": 79.79,
		"Contract": 9.78,
		"Part-time": 7.83,
		"Temporary": 0.96,
		"Internship": 0.79,
		"Volunteer": 0.45,
		"Other": 0.39
	},
	"postings": [
		93, 61, 51, 153, 5901, 6758, 256, 1243, 8526, 110, 8327, 5756, 15, 21, 7666, 4328, 11447,
		33603, 27550, 150
	],
	"salaries": {
		"labels": ["max_salary", "med_salary", "min_salary"],
		"median": [93000.0, 62000.0, 58000.0],
		"max": [1300000.0, 800000.0, 800000.0],
		"min": [0.0, 0.0, 0.0]
	},
	"benefits": {
		"bonus": 6145,
		"paid time off": 5190,
		"retirement plan": 1525,
		"health insurance": 1454,
		"flexible schedule": 1383,
		"stock options": 329
	}
}
